azure_genai_utils/__init__.py
azure_genai_utils/aoai.py
azure_genai_utils/graphs.py
azure_genai_utils/logger.py
azure_genai_utils/messages.py
azure_genai_utils/tokenizer.py
azure_genai_utils/tracer.py
azure_genai_utils/utils.py
azure_genai_utils/rag/__init__.py
azure_genai_utils/rag/base.py
azure_genai_utils/rag/pdf.py
azure_genai_utils/stt/__init__.py
azure_genai_utils/stt/augment.py
azure_genai_utils/stt/bg-noise.mp3
azure_genai_utils/stt/stt_generator.py
azure_genai_utils/synthetic/__init__.py
azure_genai_utils/synthetic/qa_generator.py
azure_genai_utils/synthetic/prompt_templates/en/prompt_qa_boolean.txt
azure_genai_utils/synthetic/prompt_templates/en/prompt_qa_conversation.txt
azure_genai_utils/synthetic/prompt_templates/en/prompt_qa_conversation_modify.txt
azure_genai_utils/synthetic/prompt_templates/en/prompt_qa_long_answer.txt
azure_genai_utils/synthetic/prompt_templates/en/prompt_qa_short_answer.txt
azure_genai_utils/synthetic/prompt_templates/en/prompt_qa_summary.txt
azure_genai_utils/synthetic/prompt_templates/ko/prompt_qa_boolean.txt
azure_genai_utils/synthetic/prompt_templates/ko/prompt_qa_conversation.txt
azure_genai_utils/synthetic/prompt_templates/ko/prompt_qa_conversation_modify.txt
azure_genai_utils/synthetic/prompt_templates/ko/prompt_qa_long_answer.txt
azure_genai_utils/synthetic/prompt_templates/ko/prompt_qa_short_answer.txt
azure_genai_utils/synthetic/prompt_templates/ko/prompt_qa_summary.txt
azure_genai_utils/tools/__init__.py
azure_genai_utils/tools/bing.py
azure_genai_utils/tools/time.py
azure_genai_utils-0.0.2.21.dist-info/licenses/LICENSE
azure_genai_utils-0.0.2.21.dist-info/METADATA
azure_genai_utils-0.0.2.21.dist-info/WHEEL
azure_genai_utils-0.0.2.21.dist-info/top_level.txt
azure_genai_utils-0.0.2.21.dist-info/RECORD
