Metadata-Version: 2.4
Name: azure-genai-utils
Version: 0.0.2.21
Summary: Utility functions for Azure GenAI
Home-page: https://github.com/daekeun-ml/azure-genai-utils
License: Apache License 2.0
Keywords: azure,genai,azure-genai-utils,azure-genai,langchain,microsoft,bing,langgraph
Classifier: Programming Language :: Python :: 3
Classifier: Programming Language :: Python :: 3.10
Classifier: Programming Language :: Python :: 3.11
Classifier: Programming Language :: Python :: 3.12
Classifier: Programming Language :: Python :: 3.13
Requires-Python: >=3.10
License-File: LICENSE
Requires-Dist: audiomentations>=0.41.0
Requires-Dist: azure-ai-contentsafety>=1.0.0
Requires-Dist: azure-ai-documentintelligence>=1.0.2
Requires-Dist: azure-ai-evaluation>=1.7.0
Requires-Dist: azure-ai-inference>=1.0.0b9
Requires-Dist: azure-ai-projects>=1.0.0b11
Requires-Dist: azure-cognitiveservices-speech>=1.44.0
Requires-Dist: azure-identity>=1.23.0
Requires-Dist: langchain>=0.3.25
Requires-Dist: langchain-community>=0.3.24
Requires-Dist: langchain-openai>=0.3.18
Requires-Dist: langgraph>=0.4.5
Requires-Dist: openai>=1.82.0
Requires-Dist: pdfplumber>=0.11.6
Requires-Dist: pybase64>=1.4.1
Requires-Dist: python-dotenv>=1.1.0
Requires-Dist: tiktoken>=0.9.0
Dynamic: classifier
Dynamic: description
Dynamic: description-content-type
Dynamic: home-page
Dynamic: keywords
Dynamic: license
Dynamic: license-file
Dynamic: requires-dist
Dynamic: requires-python
Dynamic: summary
